rich_reg_replace/__init__.py
rich_reg_replace-1.0.1.dist-info/entry_points.txt
rich_reg_replace-1.0.1.dist-info/LICENSE
rich_reg_replace-1.0.1.dist-info/WHEEL
rich_reg_replace-1.0.1.dist-info/METADATA
rich_reg_replace-1.0.1.dist-info/RECORD
