Metadata-Version: 2.1
Name: rich_reg_replace
Version: 1.0.1
Summary: Search and replace using regular expressions with a "rich" frontend.
Author-email: Leon Dionne <ldionne@dridesign.sh.cn>
Classifier: License :: OSI Approved :: GNU General Public License v3 or later (GPLv3+)
Requires-Dist: rich >= 13.7.1
Project-URL: Home, https://github.com/Zen-Master-SoSo/rich_reg_replace
